comai/__init__.py
comai/__main__.py
comai/animations.py
comai/cli.py
comai/config.py
comai/context.py
comai/history.py
comai/menu.py
comai/translation.py
comai-0.1.0.dist-info/METADATA
comai-0.1.0.dist-info/WHEEL
comai-0.1.0.dist-info/entry_points.txt
comai-0.1.0.dist-info/licenses/LICENSE
comai-0.1.0.dist-info/RECORD
