Metadata-Version: 2.1
Name: comai
Version: 0.1.0
Summary: AI powered console assistant
Project-URL: homepage, https://github.com/ricopinazo/comai
Project-URL: repository, https://github.com/ricopinazo/comai
Project-URL: issues, https://github.com/ricopinazo/comai/issues
Author-email: Pedro Rico <ricopinazo@gmail.com>
License:                     GNU GENERAL PUBLIC LICENSE
License-File: LICENSE
Classifier: License :: OSI Approved :: GNU General Public License v3 (GPLv3)
Classifier: Operating System :: MacOS
Classifier: Operating System :: OS Independent
Classifier: Operating System :: Unix
Classifier: Programming Language :: Python :: 3
Requires-Python: >=3.7
Requires-Dist: cryptography==40.0.2
Requires-Dist: openai==0.27.5
Requires-Dist: termcolor==2.3.0
Requires-Dist: typer==0.9.0
Provides-Extra: test
Requires-Dist: hatchling; extra == 'test'
Requires-Dist: pytest; extra == 'test'
Requires-Dist: python-dotenv; extra == 'test'
